tensorboxsdk/__init__.py
tensorboxsdk/tensorboxsdk.py
tensorboxsdk-1.0.2.dist-info/LICENSE
tensorboxsdk-1.0.2.dist-info/METADATA
tensorboxsdk-1.0.2.dist-info/WHEEL
tensorboxsdk-1.0.2.dist-info/top_level.txt
tensorboxsdk-1.0.2.dist-info/RECORD
