Metadata-Version: 2.1
Name: tensorboxsdk
Version: 1.0.2
Summary: Pytnon bindings for the TensorBox API
Home-page: https://github.com/tensorbox/python_sdk
Author: TensorBox
Author-email: gettensorbox@gmail.com
License: UNKNOWN
Project-URL: Bug Tracker, https://github.com/tensorbox/python_sdk/issues
Platform: UNKNOWN
Classifier: Programming Language :: Python :: 3
Classifier: License :: OSI Approved :: MIT License
Classifier: Operating System :: OS Independent
Requires-Python: >=3.6
License-File: LICENSE
